env_setter/__init__.py
env_setter/cli.py
env_setter/constants.py
env_setter/envs.py
env_setter/exceptions.py
env_setter/initialize_shell.py
env_setter/parser.py
env_setter/py.typed
env_setter-0.1.0.dist-info/METADATA
env_setter-0.1.0.dist-info/WHEEL
env_setter-0.1.0.dist-info/entry_points.txt
env_setter-0.1.0.dist-info/RECORD
