Metadata-Version: 2.4
Name: env-setter
Version: 0.1.0
Summary: Easily switch between multiple environment variables with the same name.
Project-URL: Repository, https://github.com/raspuchin/envo.git
Project-URL: Issues, https://github.com/raspuchin/envo/issues
Author-email: Sachin Pothukuchi <sachin.pothukuchi@gmail.com>
License-Expression: Apache-2.0
Classifier: Development Status :: 4 - Beta
Classifier: Intended Audience :: Developers
Classifier: Programming Language :: Python :: 3
Classifier: Programming Language :: Python :: 3.10
Classifier: Programming Language :: Python :: 3.11
Classifier: Programming Language :: Python :: 3.12
Classifier: Programming Language :: Python :: 3.13
Classifier: Programming Language :: Python :: 3.14
Classifier: Topic :: System :: Shells
Requires-Python: >=3.13
Requires-Dist: typer>=0.20.0
